spreco/__init__.py
spreco/bart_tf.py
spreco/exporter.py
spreco/sampler.py
spreco/trainer.py
spreco/common/__init__.py
spreco/common/custom_adam.py
spreco/common/diff_yaml.py
spreco/common/logger.py
spreco/common/ops.py
spreco/common/options.py
spreco/common/pipe.py
spreco/common/sampling_pattern.py
spreco/common/utils.py
spreco/dataflow/__init__.py
spreco/dataflow/base.py
spreco/dataflow/common.py
spreco/dataflow/concurrency.py
spreco/dataflow/parallel_map.py
spreco/model/__init__.py
spreco/model/gmm.py
spreco/model/logistic_loss.py
spreco/model/ncsn.py
spreco/model/nn.py
spreco/model/pixelcnn.py
spreco/model/refine_net.py
spreco/model/refine_net_sde.py
spreco/model/sde.py
spreco/model/sde2.py
spreco/model/toy.py
spreco/model/utils.py
spreco-0.0.4.dist-info/LICENSE
spreco-0.0.4.dist-info/LICENSE_bart
spreco-0.0.4.dist-info/LICENSE_logger
spreco-0.0.4.dist-info/METADATA
spreco-0.0.4.dist-info/WHEEL
spreco-0.0.4.dist-info/top_level.txt
spreco-0.0.4.dist-info/RECORD
