Metadata-Version: 2.1
Name: spreco
Version: 0.0.4
Summary: Generative image priors for MRI image reconstruction
Author-email: Guanxiong Luo <guanxiong.luo@med.uni-goettingen.de>
Project-URL: Homepage, https://github.com/mrirecon/spreco
Project-URL: Bug Tracker, https://github.com/mrirecon/spreco/issues
Keywords: MRI reconstruction,generative model,image priors,sampling
Classifier: Programming Language :: Python :: 3
Classifier: License :: OSI Approved :: BSD License
Classifier: Operating System :: POSIX :: Linux
Requires-Python: >=3.7
License-File: LICENSE
License-File: LICENSE_bart
License-File: LICENSE_logger
Requires-Dist: tensorflow
Requires-Dist: tf-slim ==1.1.0
Requires-Dist: numpy
Requires-Dist: pillow
Requires-Dist: matplotlib
Requires-Dist: scikit-image
Requires-Dist: pyyaml
Requires-Dist: tqdm
